<schema>
  <name>Salary</name>
  <columns>
    <column>
      <name>id</name>
      <title>ID</title>
      <ldmType>ATTRIBUTE</ldmType>
    </column>
    <column>
      <name>employee</name>
      <title>Employee</title>
      <ldmType>REFERENCE</ldmType>
      <pk>id</pk>
      <pkSchema>employee</pkSchema>  
    </column>
    <column>
      <name>salary</name>
      <title>Salary</title>
      <ldmType>FACT</ldmType>
    </column>
    <column>
      <name>payday</name>
      <title>Pay Day</title>
      <ldmType>DATE</ldmType>
    </column>
  </columns>
</schema>